my_cookies/my_cookies.py
my_cookies-0.1.5.data/scripts/my_cookies
my_cookies-0.1.5.dist-info/LICENSE.txt
my_cookies-0.1.5.dist-info/METADATA
my_cookies-0.1.5.dist-info/WHEEL
my_cookies-0.1.5.dist-info/top_level.txt
my_cookies-0.1.5.dist-info/RECORD
